xncml/__init__.py
xncml/core.py
xncml/parser.py
xncml/generated/__init__.py
xncml/generated/_ncml_2_2.py
xncml-0.5.1.dist-info/licenses/LICENSE
xncml-0.5.1.dist-info/WHEEL
xncml-0.5.1.dist-info/METADATA
xncml-0.5.1.dist-info/RECORD
