Metadata-Version: 2.4
Name: xncml
Version: 0.5.1
Summary: Tools for manipulating and opening NCML (NetCDF Markup) files with/for xarray
Keywords: xncml,xarray,netcdf,ncml
Author-email: Anderson Banihirwe <abanihi@ucar.edu>, David Huard <david.huard@gmail.com>
Maintainer-email: Abel Aoun <aoun.abel@gmail.com>, David Huard <david.huard@gmail.com>, Trevor James Smith <smith.trevorj@ouranos.ca>
Requires-Python: >=3.10.0
Classifier: Development Status :: 4 - Beta
Classifier: Intended Audience :: Developers
Classifier: Intended Audience :: Science/Research
Classifier: License :: OSI Approved :: Apache Software License
Classifier: Natural Language :: English
Classifier: Operating System :: OS Independent
Classifier: Programming Language :: Python :: 3
Classifier: Programming Language :: Python :: 3.10
Classifier: Programming Language :: Python :: 3.11
Classifier: Programming Language :: Python :: 3.12
Classifier: Programming Language :: Python :: 3.13
Classifier: Programming Language :: Python :: Implementation :: CPython
Classifier: Topic :: Scientific/Engineering :: Atmospheric Science
License-File: LICENSE
Requires-Dist: cftime
Requires-Dist: dask
Requires-Dist: netCDF4
Requires-Dist: psutil
Requires-Dist: xarray
Requires-Dist: xmltodict
Requires-Dist: xsdata
Requires-Dist: xncml[dev] ; extra == "all"
Requires-Dist: xncml[docs] ; extra == "all"
Requires-Dist: bump-my-version >=0.30.1 ; extra == "dev"
Requires-Dist: coverage >=7.5.0 ; extra == "dev"
Requires-Dist: flake8 >=7.1.1 ; extra == "dev"
Requires-Dist: flake8-rst-docstrings >=0.3.0 ; extra == "dev"
Requires-Dist: flit >=3.10.1,<4.0 ; extra == "dev"
Requires-Dist: mypy >=1.14.1 ; extra == "dev"
Requires-Dist: numpydoc >=1.8.0 ; extra == "dev"
Requires-Dist: pip >=25.0 ; extra == "dev"
Requires-Dist: pre-commit >=3.5.0 ; extra == "dev"
Requires-Dist: pytest >=8.3.2 ; extra == "dev"
Requires-Dist: pytest-cov >=5.0.0 ; extra == "dev"
Requires-Dist: ruff >=0.9.0 ; extra == "dev"
Requires-Dist: tox >=4.24.1 ; extra == "dev"
Requires-Dist: watchdog >=4.0.0 ; extra == "dev"
Requires-Dist: ipykernel ; extra == "docs"
Requires-Dist: ipython ; extra == "docs"
Requires-Dist: jupyter_client ; extra == "docs"
Requires-Dist: nbsphinx >=0.9.5 ; extra == "docs"
Requires-Dist: sphinx >=7.0.0 ; extra == "docs"
Requires-Dist: sphinx-codeautolink >=0.16.2 ; extra == "docs"
Requires-Dist: sphinx-copybutton ; extra == "docs"
Requires-Dist: sphinx-rtd-theme >=1.0 ; extra == "docs"
Project-URL: Changelog, https://xncml.readthedocs.io/en/stable/changelog.html
Project-URL: Homepage, https://xncml.readthedocs.io/
Project-URL: Issue tracker, https://github.com/xarray-contrib/xncml/issues
Project-URL: Source, https://github.com/xarray-contrib/xncml
Provides-Extra: all
Provides-Extra: dev
Provides-Extra: docs
